leaky/__init__.py
leaky/api.py
leaky/base.py
leaky/interface.py
leaky/memory.py
leaky/monitors.py
leaky/networkx_copy.py
leaky/options.py
leaky/output.py
leaky/reports.py
leaky/snapshots.py
leaky/themes.py
leaky/utils.py
leaky/mcp_server/__init__.py
leaky/mcp_server/main.py
python_leaky-0.5.2.dist-info/licenses/LICENSE
tests/__init__.py
tests/test_memory.py
tests/test_utils.py
python_leaky-0.5.2.dist-info/METADATA
python_leaky-0.5.2.dist-info/WHEEL
python_leaky-0.5.2.dist-info/entry_points.txt
python_leaky-0.5.2.dist-info/top_level.txt
python_leaky-0.5.2.dist-info/RECORD
