Metadata-Version: 2.4
Name: python-leaky
Version: 0.5.2
Summary: Finds memory leaks in Python programs
Requires-Python: ~=3.10
License-File: LICENSE
Requires-Dist: referrers>=0.12
Requires-Dist: rich>=13.7
Requires-Dist: psutil>=5.9
Requires-Dist: pydantic~=2.11
Requires-Dist: objsize>=0.7
Requires-Dist: networkx>=2.4
Provides-Extra: test
Requires-Dist: pytest~=8.4; extra == "test"
Requires-Dist: mypy~=1.16; extra == "test"
Requires-Dist: ruff>=0.12; extra == "test"
Requires-Dist: pre-commit~=4.2; extra == "test"
Requires-Dist: numpy~=2.2; extra == "test"
Provides-Extra: mcp
Requires-Dist: fastmcp<2.9,>=2.8; extra == "mcp"
Dynamic: license-file
